CYLGame/Comp.py
CYLGame/Database.py
CYLGame/Display.py
CYLGame/Frame.py
CYLGame/Game.py
CYLGame/Log.py
CYLGame/Panels.py
CYLGame/Player.py
CYLGame/SensorGame.py
CYLGame/Server.py
CYLGame/Utils.py
CYLGame/__init__.py
CYLGame/data/fonts/README.txt
CYLGame/data/fonts/terminal16x16_gs_ro.png
CYLGame/data/fonts/terminal8x8_gs_ro.png
CYLGame/data/little_python_intro.md
CYLGame/version.py
CYLGame/www/static/ace/ace.js
CYLGame/www/static/ace/ext-beautify.js
CYLGame/www/static/ace/ext-chromevox.js
CYLGame/www/static/ace/ext-elastic_tabstops_lite.js
CYLGame/www/static/ace/ext-emmet.js
CYLGame/www/static/ace/ext-error_marker.js
CYLGame/www/static/ace/ext-keybinding_menu.js
CYLGame/www/static/ace/ext-language_tools.js
CYLGame/www/static/ace/ext-linking.js
CYLGame/www/static/ace/ext-modelist.js
CYLGame/www/static/ace/ext-old_ie.js
CYLGame/www/static/ace/ext-searchbox.js
CYLGame/www/static/ace/ext-settings_menu.js
CYLGame/www/static/ace/ext-spellcheck.js
CYLGame/www/static/ace/ext-split.js
CYLGame/www/static/ace/ext-static_highlight.js
CYLGame/www/static/ace/ext-statusbar.js
CYLGame/www/static/ace/ext-textarea.js
CYLGame/www/static/ace/ext-themelist.js
CYLGame/www/static/ace/ext-whitespace.js
CYLGame/www/static/ace/keybinding-emacs.js
CYLGame/www/static/ace/keybinding-vim.js
CYLGame/www/static/ace/mode-abap.js
CYLGame/www/static/ace/mode-abc.js
CYLGame/www/static/ace/mode-actionscript.js
CYLGame/www/static/ace/mode-ada.js
CYLGame/www/static/ace/mode-apache_conf.js
CYLGame/www/static/ace/mode-applescript.js
CYLGame/www/static/ace/mode-asciidoc.js
CYLGame/www/static/ace/mode-assembly_x86.js
CYLGame/www/static/ace/mode-autohotkey.js
CYLGame/www/static/ace/mode-batchfile.js
CYLGame/www/static/ace/mode-c9search.js
CYLGame/www/static/ace/mode-c_cpp.js
CYLGame/www/static/ace/mode-cirru.js
CYLGame/www/static/ace/mode-clojure.js
CYLGame/www/static/ace/mode-cobol.js
CYLGame/www/static/ace/mode-coffee.js
CYLGame/www/static/ace/mode-coldfusion.js
CYLGame/www/static/ace/mode-csharp.js
cylgame-1.6.32.dist-info/LICENSE
cylgame-1.6.32.dist-info/WHEEL
cylgame-1.6.32.dist-info/METADATA
cylgame-1.6.32.dist-info/RECORD
