Metadata-Version: 2.1
Name: cylgame
Version: 1.6.32
Summary: UMDCYL Game Framework
Home-page: https://github.com/UMDLARS/CYLGame
License: MIT
Author: Jonathan Beaulieu
Author-email: 123.jonathan@gmail.com
Maintainer: Jonathan Beaulieu
Maintainer-email: 123.jonathan@gmail.com
Requires-Python: >=3.7,<4.0
Classifier: Development Status :: 3 - Alpha
Classifier: License :: OSI Approved :: MIT License
Classifier: Programming Language :: Python :: 3
Classifier: Programming Language :: Python :: 3.7
Classifier: Programming Language :: Python :: 3.8
Classifier: Programming Language :: Python :: 3.9
Project-URL: Repository, https://github.com/UMDLARS/CYLGame
